handy_cricket/__init__.py
handy_cricket/handy_cricket.py
handy_cricket-1.0.0.dist-info/LICENSE.txt
handy_cricket-1.0.0.dist-info/METADATA
handy_cricket-1.0.0.dist-info/WHEEL
handy_cricket-1.0.0.dist-info/top_level.txt
handy_cricket-1.0.0.dist-info/RECORD
