Metadata-Version: 2.1
Name: handy_cricket
Version: 1.0.0
Summary: A fun, interactive hand cricket game where you can play against the computer.
Author: Ramakrishna Pavan
Author-email: pavanm630@gmail.com
License: MIT
Project-URL: Source Repository, https://github.com/krishnapavan630
License-File: LICENSE.txt
